[  {    "type": "get",    "url": "/notices",    "title": "공지사항 조회",    "version": "0.1.0",    "name": "GetNotice",    "group": "Notice",    "permission": [      {        "name": "none"      }    ],    "description": "<p>Find all instances of the model matched by filter from the data source.</p>",    "parameter": {      "fields": {        "Parameter": [          {            "group": "Parameter",            "type": "String",            "optional": false,            "field": "id",            "description": "<p>The Users-ID.</p>"          }        ]      }    },    "success": {      "fields": {        "Success 200": [          {            "group": "Success 200",            "type": "String",            "optional": false,            "field": "id",            "description": "<p>id</p>"          }        ]      }    },    "filename": "js/_notice.js",    "groupTitle": "Notice",    "sampleRequest": [      {        "url": "http://52.231.200.170:8080/api/notices"      }    ]  },  {    "type": "get",    "url": "/others",    "title": "타사용자 리스트",    "header": {      "fields": {        "User": [          {            "group": "User",            "type": "String",            "optional": false,            "field": "authorization",            "description": "<p>Authorization value.</p>"          }        ]      },      "examples": [        {          "title": "Header-Example:",          "content": "{\n  \"Authorization\": \"accessTokenId\"\n}",          "type": "json"        }      ]    },    "version": "0.1.0",    "name": "GetOther",    "group": "Other",    "permission": [      {        "name": "user"      }    ],    "description": "<p>Find a model instance by {{id}} from the data source.</p>",    "parameter": {      "fields": {        "Parameter": [          {            "group": "Parameter",            "type": "String",            "optional": false,            "field": "id",            "description": "<p>userId\t.</p>"          }        ]      }    },    "success": {      "fields": {        "Success 200": [          {            "group": "Success 200",            "type": "String",            "optional": false,            "field": "id",            "description": "<p>userId.</p>"          },          {            "group": "Success 200",            "type": "Date",            "optional": false,            "field": "name",            "description": "<p>Fullname of the User.</p>"          }        ]      }    },    "error": {      "fields": {        "Error 4xx": [          {            "group": "Error 4xx",            "optional": false,            "field": "UserNotFound",            "description": "<p>The <code>id</code> of the User was not found.</p>"          }        ]      }    },    "filename": "js/_other.js",    "groupTitle": "Other",    "sampleRequest": [      {        "url": "http://52.231.200.170:8080/api/others"      }    ]  },  {    "type": "get",    "url": "/others/:id",    "title": "타사용자 조회",    "header": {      "fields": {        "User": [          {            "group": "User",            "type": "String",            "optional": false,            "field": "authorization",            "description": "<p>Authorization value.</p>"          }        ]      },      "examples": [        {          "title": "Header-Example:",          "content": "{\n  \"Authorization\": \"accessTokenId\"\n}",          "type": "json"        }      ]    },    "version": "0.1.0",    "name": "GetOther",    "group": "Other",    "permission": [      {        "name": "user"      }    ],    "description": "<p>Find a model instance by {{id}} from the data source.</p>",    "parameter": {      "fields": {        "Parameter": [          {            "group": "Parameter",            "type": "String",            "optional": false,            "field": "id",            "description": "<p>userId\t.</p>"          }        ]      }    },    "success": {      "fields": {        "Success 200": [          {            "group": "Success 200",            "type": "String",            "optional": false,            "field": "id",            "description": "<p>userId.</p>"          },          {            "group": "Success 200",            "type": "Date",            "optional": false,            "field": "name",            "description": "<p>Fullname of the User.</p>"          }        ]      }    },    "error": {      "fields": {        "Error 4xx": [          {            "group": "Error 4xx",            "optional": false,            "field": "UserNotFound",            "description": "<p>The <code>id</code> of the User was not found.</p>"          }        ]      }    },    "filename": "js/_other.js",    "groupTitle": "Other",    "sampleRequest": [      {        "url": "http://52.231.200.170:8080/api/others/:id"      }    ]  },  {    "type": "get",    "url": "/reports",    "title": "신고내역 리스트",    "header": {      "fields": {        "User": [          {            "group": "User",            "type": "String",            "optional": false,            "field": "authorization",            "description": "<p>Authorization value.</p>"          }        ]      },      "examples": [        {          "title": "Header-Example:",          "content": "{\n  \"Authorization\": \"accessTokenId\"\n}",          "type": "json"        }      ]    },    "version": "0.1.0",    "name": "GetOther",    "group": "Other",    "permission": [      {        "name": "user"      }    ],    "description": "<p>Find a model instance by {{id}} from the data source.</p>",    "parameter": {      "fields": {        "Parameter": [          {            "group": "Parameter",            "type": "String",            "optional": false,            "field": "id",            "description": "<p>userId\t.</p>"          }        ]      }    },    "success": {      "fields": {        "Success 200": [          {            "group": "Success 200",            "type": "String",            "optional": false,            "field": "id",            "description": "<p>userId.</p>"          },          {            "group": "Success 200",            "type": "Date",            "optional": false,            "field": "name",            "description": "<p>Fullname of the User.</p>"          }        ]      }    },    "error": {      "fields": {        "Error 4xx": [          {            "group": "Error 4xx",            "optional": false,            "field": "UserNotFound",            "description": "<p>The <code>id</code> of the User was not found.</p>"          }        ]      }    },    "filename": "js/_report.js",    "groupTitle": "Other",    "sampleRequest": [      {        "url": "http://52.231.200.170:8080/api/reports"      }    ]  },  {    "type": "get",    "url": "/reports/:id",    "title": "신교내역 조회",    "header": {      "fields": {        "User": [          {            "group": "User",            "type": "String",            "optional": false,            "field": "authorization",            "description": "<p>Authorization value.</p>"          }        ]      },      "examples": [        {          "title": "Header-Example:",          "content": "{\n  \"Authorization\": \"accessTokenId\"\n}",          "type": "json"        }      ]    },    "version": "0.1.0",    "name": "GetOther",    "group": "Other",    "permission": [      {        "name": "user"      }    ],    "description": "<p>Find a model instance by {{id}} from the data source.</p>",    "parameter": {      "fields": {        "Parameter": [          {            "group": "Parameter",            "type": "String",            "optional": false,            "field": "id",            "description": "<p>userId\t.</p>"          }        ]      }    },    "success": {      "fields": {        "Success 200": [          {            "group": "Success 200",            "type": "String",            "optional": false,            "field": "id",            "description": "<p>userId.</p>"          },          {            "group": "Success 200",            "type": "Date",            "optional": false,            "field": "name",            "description": "<p>Fullname of the User.</p>"          }        ]      }    },    "error": {      "fields": {        "Error 4xx": [          {            "group": "Error 4xx",            "optional": false,            "field": "UserNotFound",            "description": "<p>The <code>id</code> of the User was not found.</p>"          }        ]      }    },    "filename": "js/_report.js",    "groupTitle": "Other",    "sampleRequest": [      {        "url": "http://52.231.200.170:8080/api/reports/:id"      }    ]  },  {    "type": "delete",    "url": "/users",    "title": "사용자 계정탈퇴",    "version": "0.1.0",    "name": "DeleteUser",    "group": "User",    "permission": [      {        "name": "user"      }    ],    "description": "<p>Delete a model instance by {{id}} from the data source.</p>",    "parameter": {      "fields": {        "Parameter": [          {            "group": "Parameter",            "type": "String",            "optional": false,            "field": "id",            "description": "<p>userId\t.</p>"          }        ]      }    },    "error": {      "fields": {        "Error 4xx": [          {            "group": "Error 4xx",            "optional": false,            "field": "UserNotFound",            "description": "<p>The <code>id</code> of the User was not found.</p>"          }        ]      }    },    "filename": "js/_user.js",    "groupTitle": "User",    "sampleRequest": [      {        "url": "http://52.231.200.170:8080/api/users"      }    ]  },  {    "type": "get",    "url": "/users/:id",    "title": "사용자 조회",    "header": {      "fields": {        "User": [          {            "group": "User",            "type": "String",            "optional": false,            "field": "authorization",            "description": "<p>Authorization value.</p>"          }        ]      },      "examples": [        {          "title": "Header-Example:",          "content": "{\n  \"Authorization\": \"accessTokenId\"\n}",          "type": "json"        }      ]    },    "version": "0.1.0",    "name": "GetUser",    "group": "User",    "permission": [      {        "name": "admin",        "title": "This title is visible in version 0.1.0 and 0.2.0",        "description": ""      }    ],    "description": "<p>Find a model instance by {{id}} from the data source.</p>",    "parameter": {      "fields": {        "Parameter": [          {            "group": "Parameter",            "type": "String",            "optional": false,            "field": "id",            "description": "<p>userId\t.</p>"          }        ]      }    },    "success": {      "fields": {        "Success 200": [          {            "group": "Success 200",            "type": "String",            "optional": false,            "field": "id",            "description": "<p>userId.</p>"          },          {            "group": "Success 200",            "type": "Date",            "optional": false,            "field": "name",            "description": "<p>Fullname of the User.</p>"          }        ]      }    },    "error": {      "fields": {        "Error 4xx": [          {            "group": "Error 4xx",            "optional": false,            "field": "UserNotFound",            "description": "<p>The <code>id</code> of the User was not found.</p>"          }        ]      }    },    "filename": "js/_user.js",    "groupTitle": "User",    "sampleRequest": [      {        "url": "http://52.231.200.170:8080/api/users/:id"      }    ]  },  {    "type": "post",    "url": "/users",    "title": "사용자 로그인",    "version": "0.1.0",    "name": "LoginUser",    "group": "User",    "permission": [      {        "name": "user"      }    ],    "description": "<p>Login a user with username/email and password</p>",    "parameter": {      "fields": {        "Parameter": [          {            "group": "Parameter",            "type": "String",            "optional": false,            "field": "email",            "description": "<p>user eamil.</p>"          }        ]      }    },    "success": {      "fields": {        "Success 200": [          {            "group": "Success 200",            "type": "String",            "optional": false,            "field": "id",            "description": "<p>accessTokens.</p>"          }        ]      }    },    "filename": "js/_user.js",    "groupTitle": "User",    "sampleRequest": [      {        "url": "http://52.231.200.170:8080/api/users"      }    ],    "error": {      "fields": {        "Error 4xx": [          {            "group": "Error 4xx",            "optional": false,            "field": "NoAccessRight",            "description": "<p>Only authenticated Admins can access the data.</p>"          },          {            "group": "Error 4xx",            "optional": false,            "field": "UserNameTooShort",            "description": "<p>Minimum of 5 characters required.</p>"          }        ]      },      "examples": [        {          "title": "Response (example):",          "content": "HTTP/1.1 400 Bad Request\n{\n  \"error\": \"UserNameTooShort\"\n}",          "type": "json"        }      ]    }  },  {    "type": "post",    "url": "/users",    "title": "사용자 회원가입",    "version": "0.1.0",    "name": "PostUser",    "group": "User",    "permission": [      {        "name": "user"      }    ],    "description": "<p>Create a new instance of the model and persist it into the data source.</p>",    "parameter": {      "fields": {        "Parameter": [          {            "group": "Parameter",            "type": "String",            "optional": false,            "field": "email",            "description": "<p>user eamil.</p>"          }        ]      }    },    "success": {      "fields": {        "Success 200": [          {            "group": "Success 200",            "type": "String",            "optional": false,            "field": "id",            "description": "<p>userId.</p>"          }        ]      }    },    "filename": "js/_user.js",    "groupTitle": "User",    "sampleRequest": [      {        "url": "http://52.231.200.170:8080/api/users"      }    ],    "error": {      "fields": {        "Error 4xx": [          {            "group": "Error 4xx",            "optional": false,            "field": "NoAccessRight",            "description": "<p>Only authenticated Admins can access the data.</p>"          },          {            "group": "Error 4xx",            "optional": false,            "field": "UserNameTooShort",            "description": "<p>Minimum of 5 characters required.</p>"          }        ]      },      "examples": [        {          "title": "Response (example):",          "content": "HTTP/1.1 400 Bad Request\n{\n  \"error\": \"UserNameTooShort\"\n}",          "type": "json"        }      ]    }  }]
